LICENSE
MANIFEST.in
README.md
setup.cfg
setup.py
pydhan/__init__.py
pydhan/pydhan.py
pydhan.egg-info/PKG-INFO
pydhan.egg-info/SOURCES.txt
pydhan.egg-info/dependency_links.txt
pydhan.egg-info/requires.txt
pydhan.egg-info/top_level.txt