Metadata-Version: 2.1
Name: pydhan
Version: 0.2
Summary: The official Python client for communicating with the Dhan API
Home-page: UNKNOWN
Author: Dhan
Author-email: dhan-oss@dhan.co
License: MIT LICENSE
Platform: UNKNOWN
License-File: LICENSE
